{
	"pattrstorage" : 	{
		"name" : "gmu.env.default",
		"slots" : 		{
			"1" : 			{
				"id" : 1,
				"name" : " tic-tic",
				"data" : 				{
					"op_list" : [ "replace", "rand", 1000.0, 1.0, 0.0, ",", "replace", "pow", 14.0, ",", "mult", "sin", 20.0, 0.0, ",", "mult", "sin", 24.0, 0.0 ]
				}

			}
,
			"2" : 			{
				"id" : 2,
				"name" : "expo sinsoidÂ?e",
				"data" : 				{
					"op_list" : [ "replace", "expodecay", 4.0, ",", "mult", "sin", 28.0, 0.0 ]
				}

			}
,
			"3" : 			{
				"id" : 3,
				"name" : "expo decay ",
				"data" : 				{
					"op_list" : [ "replace", "expodecay", 4.0 ]
				}

			}
,
			"4" : 			{
				"id" : 4,
				"name" : "expo sinux 2",
				"data" : 				{
					"op_list" : [ "replace", "sin", 50.0, 0.0, ",", "mult", "expodecay", 5.0 ]
				}

			}
,
			"5" : 			{
				"id" : 5,
				"name" : "sweep mod",
				"data" : 				{
					"op_list" : [ "replace", "hanning", ",", "mult", "sin", 14.0, 0.0, ",", "mult", "repeat", 1.0, 9.0, 1.68 ]
				}

			}
,
			"6" : 			{
				"id" : 6,
				"name" : "expo bump",
				"data" : 				{
					"op_list" : [ "replace", "sin", 50.0, 0.0, ",", "add", "sin", 1.0, 0.0, ",", "mult", "expodecay", 5.0 ]
				}

			}
,
			"7" : 			{
				"id" : 7,
				"name" : "deux freq",
				"data" : 				{
					"op_list" : [ "replace", "sin", 50.0, 0.0, ",", "add", "sin", 75.0, 0.0, ",", "mult", "expodecay", 5.0 ]
				}

			}
,
			"8" : 			{
				"id" : 8,
				"name" : "sweep gratt",
				"data" : 				{
					"op_list" : [ "replace", "gauss", 0.44, ",", "replace", "repeat", 1.0, 17.0, -0.68, ",", "mult", "expodecay", 3.0, ",", "replace", "flipY", 0.5, ",", "replace", "repeat", 1.0, 5.0, 1.0 ]
				}

			}
,
			"9" : 			{
				"id" : 9,
				"name" : "bpf sin 1",
				"data" : 				{
					"op_list" : [ "replace", "sin", 50.0, 0.0, ",", "add", "sin", 1.0, 0.0, ",", "mult", "expodecay", 5.0, ",", "mult", "bpf", 0.0, 0.0, 1.0, 0.028302, 0.0, 0.186321, 1.0, 0.408019, 0.0, 0.412736, 0.0, 1.0 ]
				}

			}
,
			"10" : 			{
				"id" : 10,
				"name" : "bpf trapez ",
				"data" : 				{
					"op_list" : [ "replace", "bpf", 0.0, 0.0, 1.0, 0.061321, 1.0, 0.549528, 0.0, 1.0 ]
				}

			}
,
			"11" : 			{
				"id" : 11,
				"name" : "bpf sin 2  ",
				"data" : 				{
					"op_list" : [ "replace", "bpf", 0.0, 0.0, 1.0, 0.004717, 0.129032, 0.058962, 0.419355, 0.351415, 0.0, 1.0, ",", "replace", "pow", 2.43, ",", "mult", "sin", 200.0, 0.0 ]
				}

			}
,
			"12" : 			{
				"id" : 12,
				"name" : "blobby",
				"data" : 				{
					"op_list" : [ "replace", "gauss", 0.2, ",", "replace", "repeat", 2.23, 0.56, 1.0, ",", "mult", "constant", 3.0, ",", "add", "gauss", 0.5, ",", "mult", "constant", 0.29, ",", "replace", "rotate", -0.18, ",", "replace", "repeat", 1.0, 0.76, 1.0 ]
				}

			}
,
			"13" : 			{
				"id" : 13,
				"name" : "gratz blob",
				"data" : 				{
					"op_list" : [ "replace", "gauss", 0.2, ",", "replace", "repeat", 4.48, 0.56, 1.0, ",", "mult", "constant", 3.0, ",", "add", "gauss", 0.6, ",", "mult", "constant", 0.29, ",", "replace", "repeat", 11.0, 11.0, 1.0 ]
				}

			}
,
			"14" : 			{
				"id" : 14,
				"name" : "crickss",
				"data" : 				{
					"op_list" : [ "replace", "gauss", 0.2, ",", "replace", "repeat", 4.48, 0.56, 1.0, ",", "mult", "constant", 3.0, ",", "add", "gauss", 0.07, ",", "mult", "constant", 0.29, ",", "replace", "repeat", 11.0, 11.0, 1.0, ",", "add", "repeat", 1.0, 1.02, 1.0, ",", "mult", "bpf", 0.0, 0.0, 1.0, 0.042453, 0.0, 1.0 ]
				}

			}
,
			"15" : 			{
				"id" : 15,
				"name" : "sin noise",
				"data" : 				{
					"op_list" : [ "replace", "sin", 24.0, 0.0, ",", "mult", "bpf", 0.0, 0.0, 1.0, 0.004717, 0.032258, 0.068396, 0.0, 1.0, ",", "add", "rand", 792.0, 0.07, 0.0, ",", "mult", "bpf", 1.0, 0.0, 1.0, 0.775943, 0.0, 1.0 ]
				}

			}
,
			"16" : 			{
				"id" : 16,
				"name" : "sin noise 3",
				"data" : 				{
					"op_list" : [ "replace", "sin", 11.0, 0.0, ",", "mult", "bpf", 0.0, 0.0, 1.0, 0.004717, 0.032258, 0.068396, 0.177419, 0.688679, 0.419355, 0.745283, 1.0, 0.787736, 0.145161, 0.787736, 0.0, 1.0, ",", "add", "rand", 792.0, 0.1, 0.0, ",", "mult", "bpf", 1.0, 0.0, 1.0, 0.775943, 0.0, 1.0 ]
				}

			}
,
			"17" : 			{
				"id" : 17,
				"name" : "sin noise 2",
				"data" : 				{
					"op_list" : [ "replace", "sin", 11.0, 0.0, ",", "mult", "bpf", 0.0, 0.0, 1.0, 0.091981, 0.096774, 0.198113, 0.0, 1.0, ",", "add", "rand", 792.0, 0.13, 0.0, ",", "mult", "bpf", 1.0, 0.0, 0.387097, 0.160377, 1.0, 0.775943, 0.0, 1.0 ]
				}

			}
,
			"18" : 			{
				"id" : 18,
				"name" : "gratz blob rehauss",
				"data" : 				{
					"op_list" : [ "replace", "gauss", 0.2, ",", "replace", "repeat", 4.48, 0.56, 1.0, ",", "mult", "constant", 3.0, ",", "add", "gauss", 0.6, ",", "mult", "constant", 0.29, ",", "replace", "repeat", 11.0, 11.0, 1.0, ",", "add", "constant", 0.25 ]
				}

			}
,
			"19" : 			{
				"id" : 19,
				"name" : " gauss_bruitend",
				"data" : 				{
					"op_list" : [ "replace", "rand", 1000.0, 1.0, 0.0, ",", "mult", "bpf", 0.0, 0.0, 0.0, 0.299528, 0.016129, 0.490566, 0.064516, 0.582547, 0.645161, 0.875, 0.725806, 0.936321, 0.0, 1.0, ",", "replace", "rotate", -0.13, ",", "add", "gauss", 0.46 ]
				}

			}
,
			"20" : 			{
				"id" : 20,
				"name" : " gauss_bruitend_rept",
				"data" : 				{
					"op_list" : [ "replace", "rand", 1000.0, 1.0, 0.0, ",", "mult", "bpf", 0.0, 0.0, 0.0, 0.299528, 0.016129, 0.490566, 0.064516, 0.582547, 0.564516, 0.872642, 0.725806, 0.936321, 0.0, 1.0, ",", "replace", "rotate", -0.13, ",", "add", "gauss", 0.46, ",", "mult", "repeat", 1.0, 37.0, 8.0, ",", "replace", "rotate", -0.26 ]
				}

			}
,
			"21" : 			{
				"id" : 21,
				"name" : "bpf trapez rept",
				"data" : 				{
					"op_list" : [ "replace", "bpf", 0.0, 0.0, 1.0, 0.061321, 1.0, 0.141509, 0.112903, 0.403302, 0.0, 0.551887, 0.0, 1.0, ",", "replace", "repeat", 1.0, 37.0, 2.98 ]
				}

			}
,
			"22" : 			{
				"id" : 22,
				"name" : "cluster bruiteux",
				"data" : 				{
					"op_list" : [ "replace", "gauss", 0.2, ",", "replace", "repeat", 9.550000000000001, 217.0, 1.0, ",", "mult", "bpf", 0.0, 0.0, 1.0, 0.042453, 0.0, 1.0, ",", "add", "rand", 10365.0, 0.07, 0.0 ]
				}

			}
,
			"23" : 			{
				"id" : 23,
				"name" : "clust bruit deux",
				"data" : 				{
					"op_list" : [ "replace", "rand", 7769.0, 1.0, 0.0, ",", "mult", "bpf", 0.0, 0.0, 0.419355, 0.082547, 0.0, 0.106132, 0.548387, 0.129717, 0.0, 0.200472, 0.709677, 0.238208, 0.16129, 0.285377, 0.0, 0.32783, 0.790323, 0.341981, 0.33871, 0.400943, 0.854839, 0.46934, 0.016129, 0.490566, 0.467742, 0.533019, 0.064516, 0.582547, 0.645161, 0.646226, 0.193548, 0.738208, 0.0, 0.820755, 0.66129, 0.872642, 0.0, 0.908019, 0.725806, 0.936321, 0.0, 1.0, ",", "replace", "rotate", -0.13, ",", "add", "gauss", 0.65, ",", "mult", "repeat", 1.0, 133.0, 8.0, ",", "replace", "rotate", -0.26, ",", "replace", "repeat", 1.0, 0.62, 1.0 ]
				}

			}
,
			"24" : 			{
				"id" : 24,
				"name" : "peigne-gauss",
				"data" : 				{
					"op_list" : [ "replace", "gauss", 0.606, "::", "mult", "repeat", 1.0, 26.0, 1.0 ]
				}

			}
,
			"25" : 			{
				"id" : 25,
				"name" : "sin noise 4",
				"data" : 				{
					"op_list" : [ "replace", "bpf", 0.0, 0.0, 1.0, 0.023585, 0.096774, 0.141509, 0.0, 1.0, "::", "mult", "sin", 10.0, 0.0, "::", "add", "rand", 10000.0, 0.067, 0.0, "::", "mult", "bpf", 0.0, 0.0, 1.0, 0.004717, 1.0, 0.863208, 0.0, 1.0 ]
				}

			}
,
			"26" : 			{
				"id" : 26,
				"name" : "blackman",
				"data" : 				{
					"op_list" : [ "replace", "blackman" ]
				}

			}

		}

	}

}
